{"schemaVersion":"1.3","dateCreated":"2016-06-18T16:56:48.0442562Z","volumeIdentifier":"uc2.ark:/13960/t9j38q812","accessProfile":"open","rightsAttributes":"pd","hathitrustRecordNumber":"43255","enumerationChronology":" ","sourceInstitution":"UC","sourceInstitutionRecordNumber":"603721","oclc":["1186553"],"isbn":[],"issn":[],"lccn":["01031148"],"title":"The love letters of Bismarck; being letters to his fiancée and wife, 1846-1889; authorized by Prince Herbert von Bismarck and translated from the German under the supervision of Charlton T. Lewis.","imprint":"Harper, 1901.","lastUpdateDate":"2013-10-30 13:09:26","governmentDocument":false,"pubDate":"1901","pubPlace":"nyu","language":"eng","bibliographicFormat":"BK","genre":["not fiction"],"issuance":"monographic","typeOfResource":"text","classification":{"lcc":["DD218 .A26 1901"]},"names":["Bismarck, Otto Fürst von 1815-1898 ","Lewis, Charlton Thomas 1834-1904 ","Bismarck, Johanna von Puttkamer Fürstin von 1824-1894 "],"htBibUrl":"http://catalog.hathitrust.org/api/volumes/full/htid/uc2.ark:/13960/t9j38q812.json","handleUrl":"http://hdl.handle.net/2027/uc2.ark:/13960/t9j38q812"}
